segurata/__init__.py
segurata/enginee/__init__.py
segurata/enginee/enginee/__init__.py
segurata/enginee/enginee/items.py
segurata/enginee/enginee/middlewares.py
segurata/enginee/enginee/pipelines.py
segurata/enginee/enginee/settings.py
segurata/enginee/enginee/login/__init__.py
segurata/enginee/enginee/login/exceptions.py
segurata/enginee/enginee/login/login.py
segurata/enginee/enginee/spiders/__init__.py
segurata/enginee/enginee/spiders/auth.py
segurata/enginee/enginee/spiders/exceptions.py
segurata/enginee/enginee/user_config/__init__.py
segurata/enginee/enginee/user_config/exceptions.py
segurata/enginee/enginee/user_config/parse.py
tests/__init__.py
tests/test_user_config.py
segurata-0.1.0.dist-info/LICENSE
segurata-0.1.0.dist-info/METADATA
segurata-0.1.0.dist-info/WHEEL
segurata-0.1.0.dist-info/top_level.txt
segurata-0.1.0.dist-info/RECORD
