Metadata-Version: 2.1
Name: segurata
Version: 0.1.0
Summary: Tool to extract data from login-based websites.
Home-page: https://github.com/diegovincent/segurata
Author: Diego Rodriguez
Author-email: diego.vincent.rodriguez@gmail.com
License: UNKNOWN
Platform: UNKNOWN
Classifier: Development Status :: 3 - Alpha
Classifier: Intended Audience :: Developers
Classifier: Topic :: Software Development :: Build Tools
Classifier: License :: OSI Approved :: GNU General Public License v3 (GPLv3)
Classifier: Programming Language :: Python :: 3.7
Requires-Python: >=3.7
